setup.cfg
setup.py
colorsafe/__init__.py
colorsafe/cmd.py
colorsafe/constants.py
colorsafe/csdatastructures.py
colorsafe/debugutils.py
colorsafe/defaults.py
colorsafe/exceptions.py
colorsafe/utils.py
colorsafe.egg-info/PKG-INFO
colorsafe.egg-info/SOURCES.txt
colorsafe.egg-info/dependency_links.txt
colorsafe.egg-info/entry_points.txt
colorsafe.egg-info/requires.txt
colorsafe.egg-info/top_level.txt
colorsafe/decoder/__init__.py
colorsafe/decoder/csdecoder.py
colorsafe/decoder/csdecoder_getbounds.py
colorsafe/decoder/csdecoder_getchannels.py
colorsafe/decoder/csdecoder_manager.py
colorsafe/decoder/csimages_decoder.py
colorsafe/decoder/csinput_page.py
colorsafe/encoder/__init__.py
colorsafe/encoder/csencoder.py
colorsafe/encoder/csencoder_manager.py
colorsafe/encoder/csimages_encoder.py
test/test_e2e.py
test/test_unit.py
test/test_utils.py