Metadata-Version: 1.1
Name: colorsafe
Version: 0.1.0.dev6
Summary: A colorized archival data matrix for printing on paper.
Home-page: https://github.com/colorsafe/colorsafe
Author: Justin Bass
Author-email: colorsafeproject@gmail.com
License: UNKNOWN
Download-URL: https://github.com/colorsafe/colorsafe/releases/download/v0.1.0.dev6/colorsafe-0.1.0.dev6.tar.gz
Keywords: data,matrix,paper,color,archival,storage,printing,colorized
Platform: UNKNOWN
